{
  "파티": "PT, パテ, パーティー",
  "탱커": "T, タンク, タンカー",
  "딜러": "DPS, ディーラー, アタッカー, 火力職",
  "힐러": "H, ヒーラー",
  "주회": "周回",
  "마감": "〆",
  "방치작": "放置",
  "할": "割(예:7割=70%)",
  "기믹이해자": "ギミック理解, ギミック死",
  "이지": "イージー",
  "하드": "ハード",
  "시디문유적": "レグニディス遺跡, レグニディス, 遺跡",
  "침몽의숲": "夢沈みの森谷, 夢沈み",
  "빛감옥": "光亡, 牢",
  "소리없는도시": "都, 音無",
  "쇠락의심연": "深淵",
  "바위뱀": "蛇",
  "황령제단": "祭壇",
  "나뽀, 환상땅": "ナッポ",
  "침몽": "夢沈み",
  "사나운황금이빨": "金色, イノシシ",
  "서리오우거": "風呂",
  "화염오우거": "炎オーガ, フレイムオーガ",
  "산적두목, 산두": "ヒグマ, クマ, くま",
  "무크두목, 무두": "ムーク, ムークボス",
  "번개오우거, 번오": "サンダーオーガ, 雷オーガ",
  "맹독민의둥지, 맹독민": "ミーン, 巣",
  "환영거미게, 거미게": "カニクモ, カニ",
  "무쇠이빨": "鉄牙",
  "태풍고블린왕, 태고왕": "嵐, 嵐ゴブ",
  "성스러운날치, 날치": "スカイ, ヘヴン, ヘヴンスカイ",
  "리자드맨킹": "ギルミ, キングギルミー",
  "고블린왕, 고왕": "キングゴブ, 金ゴブ, キンゴブ",
  "무크왕": "キングムーク, キム",
  "이매진": "イマジン",
  "아이로나": "アイロナ",
  "아루나": "アルーナ",
  "티나": "ティナ",
  "로로라": "ロローラ",
  "보이스": "ボイス",
  "파파라": "ファルファラ",
  "도로시": "ドロシー",
  "바하마르": "バハマール",
  "고블린치유술사": "エルダ",
  "고블린기만술사": "トリックエルダー",
  "우울한양배추": "甘藍憂鬱者",
  "냉혹한양배추": "甘藍冷酷者",
  "검은돌군령관": "黒磊兵団の指揮官",
  "검은돌선봉관": "黒磊兵団の先鋒隊長",
  "바질리스크": "バジ, バジリスク",
  "고블린족장": "ゴブヲ, ゴブウォー, ウォーロード",
  "양배추대왕": "大王",
  "검은돌호위대장": "黒磊兵団の護衛隊長, 護衛隊長",
  "여우": "猛る獣, 猛獣",
  "붉은뿔, 염각": "炎角",
  "빙룡": "氷竜, 氷龍",
  "암룡": "闇竜, 闇龍",
  "광룡": "光竜, 光龍",
  "월드레이드": "ワルレ, ワールドレイド, わるれ",
  "부유섬레이드, 삼용, 3용": "浮島",
  "스톰블레이드": "ストームブレイド",
  "윈드나이트": "ゲイルランサー",
  "프로스트메이지": "フロストメイジ",
  "디바인아처": "ディバインアーチャー",
  "헤비가디언": "ヘヴィガーディアン",
  "실드나이트": "シールドファイター",
  "실반오라클": "ヴァーダントオラクル",
  "비트퍼포머": "ビートパフォーマー",
  "근접": "近接",
  "거합": "雷刃",
  "월광": "月影",
  "질풍": "烈風",
  "난무": "乱風",
  "늑대활": "狼弓",
  "매활": "鷹弓",
  "얼창": "氷牙",
  "얼빔": "霜天",
  "암방": "剛身",
  "막기": "剛守",
  "광휘": "光砕",
  "신방": "光盾",
  "치유": "森癒",
  "심판": "威咲",
  "음파": "狂音",
  "협주": "響奏",
  "허상의판결, 판결, 꿈2번": "虚妄断罪",
  "끝없는사유, 사유, 꿈3번": "無限思考",
  "적멸, 적멸의꿈, 꿈4번": "寂滅",
  "환상충격, 꿈5번": "イマジンインパクト",
  "강도, 꿈강도": "強度",
  "치명타": "会心",
  "행운": "幸運",
  "속공": "ファスト",
  "숙련": "器用さ",
  "만능": "万能",
  "궁극기, 궁": "ult",
  "이벤트": "イベント",
  "클리어": "クリア",
  "길드": "ギルド",
  "해무기, 해무무기, 해무": "海武器",
  "돌파, 강화": "凸",
  "불안정": "不安定",
  "침식": "虚飾",
  "머리나누기, 쉐어": "頭割り",
  "쿨타임": "CT",
  "마라톤": "マラソン",
  "새싹마크": "わかばマーク",
  "젤리빈": "豆",
  "메일스트롬": "メイルシュトローム"
}